CHANGELOG.txt
LICENSE.txt
MANIFEST.in
README.rst
setup.cfg
setup.py
intervaltree_bio/__init__.py
intervaltree_bio.egg-info/PKG-INFO
intervaltree_bio.egg-info/SOURCES.txt
intervaltree_bio.egg-info/dependency_links.txt
intervaltree_bio.egg-info/requires.txt
intervaltree_bio.egg-info/top_level.txt
intervaltree_bio.egg-info/zip-safe