Metadata-Version: 1.1
Name: intervaltree-bio
Version: 1.0.0
Summary: Interval tree convenience classes for genomic data
Home-page: https://github.com/konstantint/intervaltree-bio
Author: Konstantin Tretyakov
Author-email: kt@ut.ee
License: MIT
Keywords: interval-tree data-structure intervals tree genomics bioinformatics ucsc
Platform: UNKNOWN
Classifier: Development Status :: 4 - Beta
Classifier: Programming Language :: Python
Classifier: Intended Audience :: Science/Research
Classifier: License :: OSI Approved :: MIT License
Classifier: Topic :: Scientific/Engineering :: Bio-Informatics
Classifier: Topic :: Software Development :: Libraries
